shipyard_utils/__init__.py
shipyard_utils/args.py
shipyard_utils/blake-artifacts/vvv-blueprints/variables/a.pickle
shipyard_utils/body
shipyard_utils/files.py
shipyard_utils/headers
shipyard_utils/logs.py
shipyard_utils/text.py
shipyard_utils/timestamps.py
shipyard_utils/webhooks.py
shipyard_utils-0.1.4.dist-info/LICENSE
shipyard_utils-0.1.4.dist-info/WHEEL
shipyard_utils-0.1.4.dist-info/METADATA
shipyard_utils-0.1.4.dist-info/RECORD
