Metadata-Version: 2.1
Name: shipyard-utils
Version: 0.1.4
Summary: Small scripts and utilities to make Shipyard Blueprint development easier.
License: Apache-2.0
Author: Blake Burch
Author-email: blake@shipyardapp.com
Requires-Python: >=3.7,<4.0
Classifier: License :: OSI Approved :: Apache Software License
Classifier: Programming Language :: Python :: 3
Classifier: Programming Language :: Python :: 3.10
Classifier: Programming Language :: Python :: 3.7
Classifier: Programming Language :: Python :: 3.8
Classifier: Programming Language :: Python :: 3.9
Requires-Dist: python-dateutil (==2.8.2)
